redenpy/__init__.py
redenpy/core.py
redenpy/db.py
redenpy-0.1.0.dist-info/licenses/LICENSE
redenpy-0.1.0.dist-info/METADATA
redenpy-0.1.0.dist-info/WHEEL
redenpy-0.1.0.dist-info/top_level.txt
redenpy-0.1.0.dist-info/RECORD
