Metadata-Version: 2.4
Name: RedenPy
Version: 0.1.0
Summary: A Python library for currency redenomination
Author-email: Faiz Qowy <faizislamicqowy@gmail.com>
Requires-Python: >=3.10
License-File: LICENSE
Dynamic: license-file
